tents_and_trees_mip_solver/__init__.py
tents_and_trees_mip_solver/puzzle.py
tents_and_trees_mip_solver/py.typed
tents_and_trees_mip_solver/solver.py
tents_and_trees_mip_solver-0.1.2.dist-info/licenses/LICENSE.txt
tents_and_trees_mip_solver-0.1.2.dist-info/METADATA
tents_and_trees_mip_solver-0.1.2.dist-info/WHEEL
tents_and_trees_mip_solver-0.1.2.dist-info/top_level.txt
tents_and_trees_mip_solver-0.1.2.dist-info/RECORD
