Metadata-Version: 2.4
Name: tents-and-trees-mip-solver
Version: 0.1.2
Summary: A Tents and Trees puzzle solver using Mixed Integer Programming (MIP)
Author: Rasmus Ørnstrup Mikkelsen
License-Expression: MIT
Project-URL: Homepage, https://github.com/DenHvideDvaerg/tents-and-trees-mip-solver
Project-URL: Bug Reports, https://github.com/DenHvideDvaerg/tents-and-trees-mip-solver/issues
Project-URL: Source, https://github.com/DenHvideDvaerg/tents-and-trees-mip-solver
Project-URL: Documentation, https://github.com/DenHvideDvaerg/tents-and-trees-mip-solver/blob/main/model.md
Keywords: puzzle,solver,mixed-integer-programming,optimization,tents-and-trees
Classifier: Programming Language :: Python :: 3
Classifier: Programming Language :: Python :: 3.9
Classifier: Programming Language :: Python :: 3.10
Classifier: Programming Language :: Python :: 3.11
Classifier: Programming Language :: Python :: 3.12
Classifier: Programming Language :: Python :: 3.13
Classifier: Topic :: Games/Entertainment :: Puzzle Games
Classifier: Topic :: Scientific/Engineering :: Mathematics
Requires-Python: >=3.9
License-File: LICENSE.txt
Requires-Dist: ortools
Dynamic: license-file
